setup.py
django_email_user_model/__init__.py
django_email_user_model/admin.py
django_email_user_model/apps.py
django_email_user_model/backends.py
django_email_user_model/models.py
django_email_user_model.egg-info/PKG-INFO
django_email_user_model.egg-info/SOURCES.txt
django_email_user_model.egg-info/dependency_links.txt
django_email_user_model.egg-info/requires.txt
django_email_user_model.egg-info/top_level.txt
django_email_user_model/migrations/0001_initial.py
django_email_user_model/migrations/__init__.py