Metadata-Version: 1.0
Name: django-email-user-model
Version: 0.1.9
Summary: Django custom user model that enable E-Mail as username
Home-page: UNKNOWN
Author: Jeff Buttars
Author-email: jeffbuttars@gmail.com
License: MIT
Platform: UNKNOWN
